dj_rest_auth_saml/__init__.py
dj_rest_auth_saml/apps.py
dj_rest_auth_saml/serializers.py
dj_rest_auth_saml/urls.py
dj_rest_auth_saml/utils.py
dj_rest_auth_saml/views.py
dj_rest_auth_saml/migrations/__init__.py
dj_rest_auth_saml-0.0.5.dist-info/METADATA
dj_rest_auth_saml-0.0.5.dist-info/WHEEL
dj_rest_auth_saml-0.0.5.dist-info/top_level.txt
dj_rest_auth_saml-0.0.5.dist-info/RECORD
